frexpy/__init__.py
frexpy/frex.py
frexpy-1.0.0.dist-info/METADATA
frexpy-1.0.0.dist-info/WHEEL
frexpy-1.0.0.dist-info/licenses/LICENSE
frexpy-1.0.0.dist-info/RECORD
